mcalf/__init__.py
mcalf/_version.py
mcalf/version.py
mcalf/models/__init__.py
mcalf/models/base.py
mcalf/models/ibis.py
mcalf/models/results.py
mcalf/profiles/__init__.py
mcalf/profiles/gaussian.py
mcalf/profiles/voigt.py
mcalf/tests/__init__.py
mcalf/tests/figure_hashes_mpl_334_ft_261.json
mcalf/tests/helpers.py
mcalf/tests/baseline_mpl_362_ft_261/test_bar.png
mcalf/tests/baseline_mpl_362_ft_261/test_bar_allbad.png
mcalf/tests/baseline_mpl_362_ft_261/test_bar_range.png
mcalf/tests/baseline_mpl_362_ft_261/test_bar_reduce.png
mcalf/tests/baseline_mpl_362_ft_261/test_class_cmap_plot.png
mcalf/tests/baseline_mpl_362_ft_261/test_ibis8542model_fitresult_plot_i0.png
mcalf/tests/baseline_mpl_362_ft_261/test_ibis8542model_fitresult_plot_i1.png
mcalf/tests/baseline_mpl_362_ft_261/test_ibis8542model_fitresult_plot_i2.png
mcalf/tests/baseline_mpl_362_ft_261/test_ibis8542model_fitresult_plot_i3.png
mcalf/tests/baseline_mpl_362_ft_261/test_ibis8542model_fitresult_plot_i4.png
mcalf/tests/baseline_mpl_362_ft_261/test_ibis8542model_fitresult_plot_i5.png
mcalf/tests/baseline_mpl_362_ft_261/test_ibis8542model_plot_i0.png
mcalf/tests/baseline_mpl_362_ft_261/test_ibis8542model_plot_i1.png
mcalf/tests/baseline_mpl_362_ft_261/test_ibis8542model_plot_i2.png
mcalf/tests/baseline_mpl_362_ft_261/test_ibis8542model_plot_i3.png
mcalf/tests/baseline_mpl_362_ft_261/test_ibis8542model_plot_i4.png
mcalf/tests/baseline_mpl_362_ft_261/test_ibis8542model_plot_i5.png
mcalf/tests/baseline_mpl_362_ft_261/test_ibis8542model_plot_indices_0-1-3.png
mcalf/tests/baseline_mpl_362_ft_261/test_ibis8542model_plot_indices_1-0-3.png
mcalf/tests/baseline_mpl_362_ft_261/test_ibis8542model_plot_no_intensity.png
mcalf/tests/baseline_mpl_362_ft_261/test_ibis8542model_plot_separate_i0.png
mcalf/tests/baseline_mpl_362_ft_261/test_ibis8542model_plot_separate_i1.png
mcalf/tests/baseline_mpl_362_ft_261/test_ibis8542model_plot_separate_i2.png
mcalf/tests/baseline_mpl_362_ft_261/test_ibis8542model_plot_separate_i3.png
mcalf-1.0.0.dist-info/LICENSE.rst
mcalf-1.0.0.dist-info/METADATA
mcalf-1.0.0.dist-info/WHEEL
mcalf-1.0.0.dist-info/top_level.txt
mcalf-1.0.0.dist-info/RECORD
