Metadata-Version: 2.1
Name: mcalf
Version: 1.0.0
Summary: "MCALF: Multi-Component Atmospheric Line Fitting"
Home-page: https://github.com/ConorMacBride/mcalf/
Author: Conor MacBride
Author-email: cmacbride01@qub.ac.uk
License: BSD 2-Clause
Project-URL: Documentation, https://mcalf.macbride.me/
Keywords: spectrum,spectra,fitting,absorption,emission,voigt
Classifier: Intended Audience :: Science/Research
Classifier: License :: OSI Approved :: BSD License
Classifier: Operating System :: OS Independent
Classifier: Programming Language :: C
Classifier: Programming Language :: Python :: 3
Classifier: Programming Language :: Python :: 3.8
Classifier: Programming Language :: Python :: 3.9
Classifier: Programming Language :: Python :: 3.10
Classifier: Programming Language :: Python :: 3.11
Classifier: Topic :: Scientific/Engineering :: Astronomy
Classifier: Topic :: Scientific/Engineering :: Physics
Requires-Python: >=3.7
License-File: LICENSE.rst
Requires-Dist: astropy (>=4.2)
Requires-Dist: matplotlib (>=3.1)
Requires-Dist: numpy (>=1.18)
Requires-Dist: pathos (>=0.2.5)
Requires-Dist: pyyaml (>=5.1)
Requires-Dist: scikit-learn (>=0.22)
Requires-Dist: scipy (>=1.4)
Provides-Extra: docs
Requires-Dist: sphinx ; extra == 'docs'
Requires-Dist: ipykernel ; extra == 'docs'
Requires-Dist: nbsphinx ; extra == 'docs'
Requires-Dist: sphinx-rtd-theme ; extra == 'docs'
Requires-Dist: sphinx-gallery ; extra == 'docs'
Requires-Dist: pytest ; extra == 'docs'
Requires-Dist: setuptools-scm ; extra == 'docs'
Provides-Extra: tests
Requires-Dist: pytest ; extra == 'tests'
Requires-Dist: pytest-cov ; extra == 'tests'
Requires-Dist: pytest-mpl ; extra == 'tests'
Requires-Dist: tox ; extra == 'tests'
